Metadata-Version: 1.0
Name: dsnd-probability-aordorica
Version: 1.2
Summary: Gaussian and Binomial  distributions
Home-page: UNKNOWN
Author: Armando Ordorica
Author-email: armandordorica@gmail.com
License: UNKNOWN
Platform: UNKNOWN
